<?xml version="1.0" encoding="UTF-8"?><record_update>
    <sys_choice action="INSERT_OR_UPDATE" field="apo_fpo_cpo" table="x_g_dis_atat_dapps_address_table" version="3">
        <sys_choice_set action="INSERT_OR_UPDATE">
            <element>apo_fpo_cpo</element>
            <name>x_g_dis_atat_dapps_address_table</name>
            <sys_class_name>sys_choice_set</sys_class_name>
            <sys_created_by>admin</sys_created_by>
            <sys_created_on>2023-04-24 17:27:04</sys_created_on>
            <sys_mod_count>0</sys_mod_count>
            <sys_name>apo_fpo_cpo</sys_name>
            <sys_package display_value="ATAT" source="x_g_dis_atat">f600233d1b154d507b782f84604bcb12</sys_package>
            <sys_policy/>
            <sys_scope display_value="ATAT">f600233d1b154d507b782f84604bcb12</sys_scope>
            <sys_update_name>sys_choice_x_g_dis_atat_dapps_address_table_apo_fpo_cpo</sys_update_name>
            <sys_updated_by>admin</sys_updated_by>
            <sys_updated_on>2023-04-24 17:27:04</sys_updated_on>
        </sys_choice_set>
        <sys_choice action="INSERT_OR_UPDATE">
            <dependent_value/>
            <element>apo_fpo_cpo</element>
            <hint/>
            <inactive>false</inactive>
            <label>Army Post Office</label>
            <language>en</language>
            <name>x_g_dis_atat_dapps_address_table</name>
            <sequence/>
            <synonyms/>
            <sys_created_by>admin</sys_created_by>
            <sys_created_on>2023-04-24 17:27:04</sys_created_on>
            <sys_domain>global</sys_domain>
            <sys_domain_path>/</sys_domain_path>
            <sys_id>073705ef479c355093e530ed436d43c7</sys_id>
            <sys_mod_count>1</sys_mod_count>
            <sys_updated_by>admin</sys_updated_by>
            <sys_updated_on>2023-04-24 17:27:08</sys_updated_on>
            <value>APO</value>
        </sys_choice>
        <sys_choice action="INSERT_OR_UPDATE">
            <dependent_value/>
            <element>apo_fpo_cpo</element>
            <hint/>
            <inactive>false</inactive>
            <label>Diplomatic Post Office</label>
            <language>en</language>
            <name>x_g_dis_atat_dapps_address_table</name>
            <sequence/>
            <synonyms/>
            <sys_created_by>admin</sys_created_by>
            <sys_created_on>2023-04-24 17:27:37</sys_created_on>
            <sys_domain>global</sys_domain>
            <sys_domain_path>/</sys_domain_path>
            <sys_id>473705ef479c355093e530ed436d43c8</sys_id>
            <sys_mod_count>1</sys_mod_count>
            <sys_updated_by>admin</sys_updated_by>
            <sys_updated_on>2023-04-24 17:27:42</sys_updated_on>
            <value>DPO</value>
        </sys_choice>
        <sys_choice action="INSERT_OR_UPDATE">
            <dependent_value/>
            <element>apo_fpo_cpo</element>
            <hint/>
            <inactive>false</inactive>
            <label>Fleet Post Office</label>
            <language>en</language>
            <name>x_g_dis_atat_dapps_address_table</name>
            <sequence/>
            <synonyms/>
            <sys_created_by>admin</sys_created_by>
            <sys_created_on>2023-04-24 17:27:19</sys_created_on>
            <sys_domain>global</sys_domain>
            <sys_domain_path>/</sys_domain_path>
            <sys_id>873705ef479c355093e530ed436d43c9</sys_id>
            <sys_mod_count>1</sys_mod_count>
            <sys_updated_by>admin</sys_updated_by>
            <sys_updated_on>2023-04-24 17:27:23</sys_updated_on>
            <value>FPO</value>
        </sys_choice>
    </sys_choice>
</record_update>
